aipkgs_sentry/__init__.py
aipkgs_sentry/helpers.py
aipkgs_sentry-1.0.6.dist-info/LICENSE.md
aipkgs_sentry-1.0.6.dist-info/METADATA
aipkgs_sentry-1.0.6.dist-info/WHEEL
aipkgs_sentry-1.0.6.dist-info/RECORD
