Metadata-Version: 2.1
Name: aipkgs-sentry
Version: 1.0.6
Summary: Sentry integration for aipy packages
Home-page: https://gitlab.com/aipy/public/packages.git
License: MIT
Keywords: ai
Author: Alexy
Author-email: alexy.ib@outlook.com
Requires-Python: >=3.11.4,<4.0.0
Classifier: License :: OSI Approved :: MIT License
Classifier: Programming Language :: Python :: 3
Classifier: Programming Language :: Python :: 3.12
Provides-Extra: flask
Requires-Dist: sentry-sdk (>=2.4.0,<3.0.0) ; extra == "flask"
Project-URL: Repository, https://gitlab.com/aipy/public/packages.git
